survlime/__init__.py
survlime/survlime_explainer.py
survlime/datasets/__init__.py
survlime/datasets/load_datasets.py
survlime/datasets/loading_utils.py
survlime/utils/__init__.py
survlime/utils/neighbours_generator.py
survlime/utils/optimization.py
survlime-0.1.1.dist-info/METADATA
survlime-0.1.1.dist-info/WHEEL
survlime-0.1.1.dist-info/top_level.txt
survlime-0.1.1.dist-info/RECORD
