Metadata-Version: 2.1
Name: survlime
Version: 0.1.1
Summary: Survival adaptation of the LIME algorithm
Home-page: https://github.com/imatge-upc/SurvLIME
Author: Carlos Hernández Pérez, Cristian Pachón García
Author-email: crherperez95@gmail.com, cc.pachon@gmail.com
License: UNKNOWN
Platform: UNKNOWN
Requires-Dist: numpy
Requires-Dist: cvxpy
Requires-Dist: scikit-learn
Requires-Dist: pandas
Provides-Extra: dev
Requires-Dist: pytest ; extra == 'dev'
